{"paginationInfo": {"startRecord": 0, "expectedRecordsPerPage": 200, "totalRecordsPerPage": 6, "totalRecords": 6}, "stores": [{"storeNumber": 22739, "address": "401 Myers St Se", "city": "Rainier", "state": "WA", "zipCode": "98576", "latitude": 46.89072, "longitude": -122.6838, "phoneNumber": "2067560929", "storeServiceBitmap": 1081408, "storeServices": [{"description": "Fresh Produce", "serviceId": 21}, {"description": "Amerigas", "serviceId": 3}, {"description": "NCI", "serviceId": 16}], "storeType": 1, "distance": 0.5, "hrsMon": "0800:2200", "hrsTue": "0800:2200", "hrsWed": "0800:2200", "hrsThu": "0800:2200", "hrsFri": "0800:2200", "hrsSat": "0800:2200", "hrsSun": "0800:2200", "inventoryStatus": 0, "productQTY": 0, "isSellable": false, "isEligibleForPickup": false, "isEligibleForShipToHome": false, "isEligibleForDelivery": false}, {"storeNumber": 20766, "address": "376 W Reynolds Ave", "city": "Centralia", "state": "WA", "zipCode": "98531-3316", "latitude": 46.7352, "longitude": -122.9571, "phoneNumber": "9713204570", "storeServiceBitmap": 32834, "storeServices": [{"description": "Amerigas", "serviceId": 3}, {"description": "Scan Only", "serviceId": 2}, {"description": "NCI", "serviceId": 16}], "storeType": 1, "distance": 16.5, "hrsMon": "0800:2200", "hrsTue": "0800:2200", "hrsWed": "0800:2200", "hrsThu": "0800:2200", "hrsFri": "0800:2200", "hrsSat": "0800:2200", "hrsSun": "0800:2200", "inventoryStatus": 0, "productQTY": 0, "isSellable": false, "isEligibleForPickup": false, "isEligibleForShipToHome": false, "isEligibleForDelivery": false}, {"storeNumber": 22596, "address": "405 E Summa St", "city": "Centralia", "state": "WA", "zipCode": "98531", "latitude": 46.70626, "longitude": -122.95482, "phoneNumber": "2066354504", "storeServiceBitmap": 34882, "storeServices": [{"description": "Amerigas", "serviceId": 3}, {"description": "Scan Only", "serviceId": 2}, {"description": "NCI", "serviceId": 16}, {"description": "FedEX", "serviceId": 12}], "storeType": 1, "distance": 17.5, "hrsMon": "0800:2200", "hrsTue": "0800:2200", "hrsWed": "0800:2200", "hrsThu": "0800:2200", "hrsFri": "0800:2200", "hrsSat": "0800:2200", "hrsSun": "0800:2200", "inventoryStatus": 0, "productQTY": 0, "isSellable": false, "isEligibleForPickup": false, "isEligibleForShipToHome": false, "isEligibleForDelivery": false}, {"storeNumber": 23192, "address": "1417 Harrison Ave", "city": "Centralia", "state": "WA", "zipCode": "98531-4528", "latitude": 46.73295, "longitude": -122.98734, "phoneNumber": "2536001641", "storeServiceBitmap": 1081408, "storeServices": [{"description": "Fresh Produce", "serviceId": 21}, {"description": "Amerigas", "serviceId": 3}, {"description": "NCI", "serviceId": 16}], "storeType": 1, "distance": 18.1, "hrsMon": "0800:2200", "hrsTue": "0800:2200", "hrsWed": "0800:2200", "hrsThu": "0800:2200", "hrsFri": "0800:2200", "hrsSat": "0800:2200", "hrsSun": "0800:2200", "inventoryStatus": 0, "productQTY": 0, "isSellable": false, "isEligibleForPickup": false, "isEligibleForShipToHome": false, "isEligibleForDelivery": false}, {"storeNumber": 20770, "address": "417 Birch Ave Sw", "city": "Napavine", "state": "WA", "zipCode": "98565", "latitude": 46.5728, "longitude": -122.9128, "phoneNumber": "5099006570", "storeServiceBitmap": 32866, "storeServices": [{"description": "Amerigas", "serviceId": 3}, {"description": "Rug Doctor", "serviceId": 4}, {"description": "Scan Only", "serviceId": 2}, {"description": "NCI", "serviceId": 16}], "storeType": 1, "distance": 24.2, "hrsMon": "0800:2200", "hrsTue": "0800:2200", "hrsWed": "0800:2200", "hrsThu": "0800:2200", "hrsFri": "0800:2200", "hrsSat": "0800:2200", "hrsSun": "0800:2200", "inventoryStatus": 0, "productQTY": 0, "isSellable": false, "isEligibleForPickup": false, "isEligibleForShipToHome": false, "isEligibleForDelivery": false}, {"storeNumber": 21160, "address": "305 W Pine", "city": "Oakville", "state": "WA", "zipCode": "98568", "latitude": 46.8412, "longitude": -123.2374, "phoneNumber": "3603587650", "storeServiceBitmap": 32866, "storeServices": [{"description": "Amerigas", "serviceId": 3}, {"description": "Rug Doctor", "serviceId": 4}, {"description": "Scan Only", "serviceId": 2}, {"description": "NCI", "serviceId": 16}], "storeType": 1, "distance": 26.6, "hrsMon": "0800:2200", "hrsTue": "0800:2200", "hrsWed": "0800:2200", "hrsThu": "0800:2200", "hrsFri": "0800:2200", "hrsSat": "0800:2200", "hrsSun": "0800:2200", "inventoryStatus": 0, "productQTY": 0, "isSellable": false, "isEligibleForPickup": false, "isEligibleForShipToHome": false, "isEligibleForDelivery": false}]}